aioredis_models/__init__.py
aioredis_models/asyncio_utils.py
aioredis_models/redis_client.py
aioredis_models/redis_double_hash.py
aioredis_models/redis_hash.py
aioredis_models/redis_key.py
aioredis_models/redis_list.py
aioredis_models/redis_model.py
aioredis_models/redis_set.py
aioredis_models/redis_string.py
aioredis_models/redis_transaction.py
e2e/__init__.py
e2e/redis_double_hash_tests.py
e2e/redis_hash_tests.py
e2e/redis_list_tests.py
e2e/redis_tests.py
e2e/redis_transaction_tests.py
aioredis_models-3.0.0.dist-info/LICENSE
aioredis_models-3.0.0.dist-info/METADATA
aioredis_models-3.0.0.dist-info/WHEEL
aioredis_models-3.0.0.dist-info/top_level.txt
aioredis_models-3.0.0.dist-info/RECORD
