Metadata-Version: 2.1
Name: aioredis-models
Version: 3.0.0
Summary: Model Redis data structures
Home-page: https://github.com/qcrisw/aioredis-models
Author: QCRI Software Group
Author-email: qcriswgroup@hbku.edu.qa
License: MIT
Keywords: redis,asyncio,data-structures,models
Platform: UNKNOWN
Classifier: License :: OSI Approved :: MIT License
Classifier: Programming Language :: Python :: 3.6
Classifier: Programming Language :: Python :: 3.7
Classifier: Programming Language :: Python :: 3.8
Classifier: Programming Language :: Python :: 3.9
Requires-Dist: aioredis (==1.3.1)
